zotasdk/__init__.py
zotasdk/client.py
zotasdk/config.py
zotasdk/constants.py
zotasdk/exceptions.py
zotasdk/helpers.py
zotasdk/mg_comms.py
zotasdk/testing_tools.py
zotasdk/urls.py
zotasdk/mg_requests/__init__.py
zotasdk/mg_requests/callback.py
zotasdk/mg_requests/card_deposit_request.py
zotasdk/mg_requests/card_deposit_response.py
zotasdk/mg_requests/deposit_request.py
zotasdk/mg_requests/deposit_response.py
zotasdk/mg_requests/mg_request.py
zotasdk/mg_requests/objects.py
zotasdk/mg_requests/order_status_request.py
zotasdk/mg_requests/order_status_response.py
zotasdk/mg_requests/payout_request.py
zotasdk/mg_requests/payout_response.py
zotasdk/mg_requests/response.py
zotasdk/mg_requests/validation.py
zotasdk/tests/__init__.py
zotasdk/tests/conftest.py
zotasdk/tests/mocks.py
zotasdk/tests/local/__init__.py
zotasdk/tests/local/test_client_configuration.py
zotasdk/tests/local/test_core.py
zotasdk/tests/local/test_deposit.py
zotasdk/tests/local/test_order_status.py
zotasdk/tests/local/test_payout.py
zotasdk/tests/local/test_signatures.py
zotasdk/tests/online/__init__.py
zotasdk/tests/online/test_sandbox_deposit.py
zotasdk-1.2.2.dist-info/LICENSE
zotasdk-1.2.2.dist-info/METADATA
zotasdk-1.2.2.dist-info/WHEEL
zotasdk-1.2.2.dist-info/top_level.txt
zotasdk-1.2.2.dist-info/RECORD
