Metadata-Version: 2.1
Name: zotasdk
Version: 1.2.2
Summary: SDK Implementation of Zota's REST API for merchants.
Home-page: https://pypi.org/p/zotasdk
Author: Zota Technology Pte Ltd
Author-email: Zota Technology Pte Ltd <open-source@zota.com>
License: Copyright 2020-2024 Zota Technology LTD
Project-URL: Homepage, https://github.com/zota/python-sdk
Project-URL: Bug Tracker, https://github.com/zota/python-sdk/issues
Classifier: Development Status :: 6 - Mature
Classifier: Intended Audience :: Information Technology
Classifier: License :: OSI Approved :: Apache Software License
Classifier: Operating System :: OS Independent
Classifier: Programming Language :: Python :: 3
Classifier: Topic :: Software Development :: Libraries :: Python Modules
Requires-Python: >=3.8
License-File: LICENSE
Requires-Dist: requests
